{"is_source_file": true, "format": "JavaScript", "description": "This file is an ESLint configuration file written in JavaScript. It sets up linting rules and environment settings for a JavaScript/React project.", "external_files": ["eslint-plugin-react-hooks", "eslint-plugin-react-refresh", "eslint/config"], "external_methods": ["reactHooks.configs['recommended-latest']", "reactRefresh.configs.vite", "globalIgnores"], "published": ["defineConfig"], "classes": [], "methods": [{"name": "defineConfig", "description": "Function to define and export the ESLint configuration object."}], "calls": ["globalIgnores(['dist'])"], "search-terms": ["eslint.config.js", "eslint", "JavaScript ESLint configuration", "react-hooks", "react-refresh", "defineConfig", "eslint plugin"], "state": 2, "file_id": 4, "knowledge_revision": 20, "git_revision": "da99a090293cd1da46f3e5c534adae4c24e48bc4", "ctags": [], "hash": "a849a55f4e916bdeb367145bc02b8c78", "format-version": 4, "code-base-name": "recipe_app_frontend", "filename": "recipe_app_frontend/eslint.config.js", "revision_history": [{"20": "da99a090293cd1da46f3e5c534adae4c24e48bc4"}]}